Metadata-Version: 1.0
Name: dopetools
Version: 0.1.1
Summary: Useful tools for the DOPE project.
Home-page: UNKNOWN
Author: Badruu
Author-email: badrus@propulsionacademy.com
License: MIT
Platform: UNKNOWN
